topozarr/__init__.py
topozarr/chunking.py
topozarr/coarsen.py
topozarr/metadata.py
topozarr/pyramid.py
topozarr-0.0.3.dist-info/WHEEL
topozarr-0.0.3.dist-info/METADATA
topozarr-0.0.3.dist-info/RECORD
