Metadata-Version: 2.3
Name: topozarr
Version: 0.0.3
Summary: Lightweight multiscale zarr
Requires-Dist: dask>=2025.12.0
Requires-Dist: xarray>=2025.9.0
Requires-Dist: xproj>=0.2.1
Requires-Python: >=3.11
